gouge/__init__.py
gouge/colourcli.py
gouge/filters.py
gouge/parseable.py
gouge/preformatters.py
gouge/py.typed
gouge-2.2.5.dist-info/METADATA
gouge-2.2.5.dist-info/WHEEL
gouge-2.2.5.dist-info/top_level.txt
gouge-2.2.5.dist-info/RECORD
