Metadata-Version: 2.1
Name: gouge
Version: 2.2.5
Summary: Collection of logging formatters.
Author-email: Michel Albert <michel@albert.lu>
License: BSD-3-Clause
Project-URL: Repository, https://github.com/exhuma/gouge
Classifier: Development Status :: 4 - Beta
Classifier: Environment :: Console
Classifier: Intended Audience :: Developers
Classifier: License :: OSI Approved :: MIT License
Classifier: Operating System :: OS Independent
Classifier: Programming Language :: Python
Classifier: Programming Language :: Python :: 2
Classifier: Programming Language :: Python :: 3
Classifier: Topic :: Other/Nonlisted Topic
Classifier: Topic :: Software Development :: Libraries
Classifier: Topic :: System :: Logging
Requires-Python: >=3.7
Requires-Dist: colorama
Provides-Extra: dev
Requires-Dist: furo ; extra == 'dev'
Requires-Dist: types-colorama ; extra == 'dev'
Provides-Extra: test
Requires-Dist: pytest ; extra == 'test'
